codetopackage/Library_CopyFunction.py
codetopackage/Library_EqualityCheck.py
codetopackage/Library_FilePathExists.py
codetopackage/Library_FileReadAsText.py
codetopackage/Library_FileWriteText.py
codetopackage/Library_HardDifferenceSmallCheck.py
codetopackage/Library_IsPrime.py
codetopackage/Library_IterableSubset.py
codetopackage/Library_LibraryDependencyList.py
codetopackage/Library_LibraryExtractBodyString.py
codetopackage/Library_NestedObjectFlatten.py
codetopackage/Library_OrderOfMagnitudeRatio.py
codetopackage/Library_OrderOfMagnitudeRatioSmallCheck.py
codetopackage/Library_PrintExceptionObject.py
codetopackage/Library_PrintFullTestSuccess.py
codetopackage/Library_StringExpressionToSympyExpression.py
codetopackage/Library_StringFilePathGetDirectory.py
codetopackage/Library_StringSubstringFindAll.py
codetopackage/Library_SympyExpressionCoefficients.py
codetopackage/Library_SympyExpressionEquality.py
codetopackage/Library_SympyExpressionPrintInfo.py
codetopackage/Library_SympyExpressionRestrictVariables.py
codetopackage/Library_SympyExpressionSimplify.py
codetopackage/Library_SympyExpressionToPythonFunction.py
codetopackage/Library_SystemDirectoryCreateSafe.py
codetopackage/Library_TestLooper.py
codetopackage/Library_TestResultCheck.py
codetopackage/Type_HashTable.py
codetopackage/Type_Iterable.py
codetopackage/Type_Number.py
codetopackage/Type_SympyExpression.py
codetopackage/__init__.py
codetopackage/create_package.py
codetopackage/test_codetopackage.py
codetopackage/default/.gitignore
codetopackage/default/.readthedocs.yml
codetopackage/default/__init__.py
codetopackage/default/setup.py
codetopackage/default/docs/Makefile
codetopackage/default/docs/source/api.rst
codetopackage/default/docs/source/conf.py
codetopackage/default/docs/source/contributors.rst
codetopackage/default/docs/source/examples.rst
codetopackage/default/docs/source/index.rst
codetopackage/default/docs/source/install.rst
codetopackage/default/docs/source/requirements.txt
codetopackage-1.0.4.dist-info/METADATA
codetopackage-1.0.4.dist-info/WHEEL
codetopackage-1.0.4.dist-info/top_level.txt
codetopackage-1.0.4.dist-info/RECORD
