Metadata-Version: 2.1
Name: codetopackage
Version: 1.0.4
Summary: UNKNOWN
Home-page: UNKNOWN
Author: Justin Pierel
Author-email: justin.pierel@gmail.com
License: UNKNOWN
Platform: UNKNOWN
Requires-Dist: numpy
Requires-Dist: sphinx-rtd-theme
Requires-Dist: sympy
Requires-Dist: scipy
Requires-Dist: cffi
Requires-Dist: astropy
Requires-Dist: pytest-astropy
